tools_mrcode/__init__.py
tools_mrcode/file_util.py
tools_mrcode/json_util.py
tools_mrcode/logging_util.py
tools_mrcode/mail_util.py
tools_mrcode/time_util.py
tools_mrcode-0.0.5.dist-info/LICENSE
tools_mrcode-0.0.5.dist-info/METADATA
tools_mrcode-0.0.5.dist-info/WHEEL
tools_mrcode-0.0.5.dist-info/top_level.txt
tools_mrcode-0.0.5.dist-info/RECORD
