Metadata-Version: 2.1
Name: tools_mrcode
Version: 0.0.5
Summary: 学习使用 Python 过程中，编写的一些工具
Author-email: mrcode <99299684@qq.com>
Project-URL: Homepage, https://github.com/zq99299/tools-mrcode
Project-URL: Issues, https://github.com/zq99299/tools-mrcode/issues
Classifier: Programming Language :: Python :: 3
Classifier: License :: OSI Approved :: MIT License
Classifier: Operating System :: OS Independent
Requires-Python: >=3.10
License-File: LICENSE
Requires-Dist: jsonpath-ng ==1.6.1
